strapalchemy/__init__.py
strapalchemy/logging/__init__.py
strapalchemy/logging/handlers.py
strapalchemy/logging/logger.py
strapalchemy/models/__init__.py
strapalchemy/models/base.py
strapalchemy/services/__init__.py
strapalchemy/services/field_selector.py
strapalchemy/services/filter_builder.py
strapalchemy/services/operator_handler.py
strapalchemy/services/paginator.py
strapalchemy/services/population_builder.py
strapalchemy/services/query_optimizer.py
strapalchemy/services/search_engine.py
strapalchemy/services/serializer.py
strapalchemy/services/sort_builder.py
strapalchemy/services/sync_paginator.py
strapalchemy/services/sync_query_optimizer.py
strapalchemy/services/type_converter.py
strapalchemy-0.2.5.dist-info/METADATA
strapalchemy-0.2.5.dist-info/WHEEL
strapalchemy-0.2.5.dist-info/licenses/LICENSE
strapalchemy-0.2.5.dist-info/RECORD
