Metadata-Version: 2.4
Name: strapalchemy
Version: 0.2.5
Summary: Enhanced SQLAlchemy query builder with advanced filtering, sorting, pagination, and search capabilities.
Project-URL: Homepage, https://github.com/faisalcayunda/strapalchemy
Project-URL: Documentation, https://github.com/faisalcayunda/strapalchemy#readme
Project-URL: Repository, https://github.com/faisalcayunda/strapalchemy
Project-URL: Issues, https://github.com/faisalcayunda/strapalchemy/issues
Author-email: Faisal Nugraha Cayunda <faisal.nugraha.c@gmail.com>
Maintainer-email: Faisal Nugraha Cayunda <faisal.nugraha.c@gmail.com>
License: MIT
License-File: LICENSE
Keywords: database,filtering,orm,pagination,query-builder,search,sqlalchemy,strapi
Classifier: Development Status :: 3 - Alpha
Classifier: Intended Audience :: Developers
Classifier: License :: OSI Approved :: MIT License
Classifier: Programming Language :: Python :: 3
Classifier: Programming Language :: Python :: 3.12
Classifier: Programming Language :: Python :: 3.13
Classifier: Programming Language :: Python :: 3.14
Classifier: Topic :: Database
Classifier: Topic :: Software Development :: Libraries :: Python Modules
Classifier: Typing :: Typed
Requires-Python: >=3.12
Requires-Dist: python-dateutil>=2.9.0.post0
Requires-Dist: rich>=13.0.0
Requires-Dist: sqlalchemy>=2.0.45
Provides-Extra: dev
Requires-Dist: aiosqlite>=0.19.0; extra == 'dev'
Requires-Dist: black>=24.0.0; extra == 'dev'
Requires-Dist: greenlet>=3.0.0; extra == 'dev'
Requires-Dist: mypy>=1.8.0; extra == 'dev'
Requires-Dist: pytest-asyncio>=0.23.0; extra == 'dev'
Requires-Dist: pytest-cov>=4.0.0; extra == 'dev'
Requires-Dist: pytest>=8.0.0; extra == 'dev'
Requires-Dist: ruff>=0.1.0; extra == 'dev'
Requires-Dist: types-python-dateutil>=2.9.0; extra == 'dev'
